{"trial_id": "eaafd1b7ef89eea3e7886c5b5fd3da9d", "hyperparameters": {"space": [{"class_name": "Int", "config": {"name": "nb_filters", "default": null, "conditions": [], "min_value": 32, "max_value": 512, "step": 32, "sampling": null}}, {"class_name": "Int", "config": {"name": "kernel_size", "default": null, "conditions": [], "min_value": 3, "max_value": 7, "step": 2, "sampling": null}}, {"class_name": "Float", "config": {"name": "learning_rate", "default": 0.001, "conditions": [], "min_value": 1e-05, "max_value": 0.01, "step": null, "sampling": "log"}}], "values": {"nb_filters": 352, "kernel_size": 5, "learning_rate": 2.5732638229762463e-05}}, "metrics": {"metrics": {"loss": {"direction": "min", "observations": [{"value": [0.0036137980641797185], "step": 0}]}, "output_layer_1_loss": {"direction": "min", "observations": [{"value": [0.0015142119373194873], "step": 0}]}, "output_layer_2_loss": {"direction": "min", "observations": [{"value": [0.0020995866507291794], "step": 0}]}, "output_layer_1_binary_accuracy": {"direction": "min", "observations": [{"value": [0.81817826628685], "step": 0}]}, "output_layer_2_binary_accuracy": {"direction": "min", "observations": [{"value": [0.7542427480220795], "step": 0}]}, "val_loss": {"direction": "min", "observations": [{"value": [0.005572929745540023], "step": 0}]}, "val_output_layer_1_loss": {"direction": "min", "observations": [{"value": [0.002879325649701059], "step": 0}]}, "val_output_layer_2_loss": {"direction": "min", "observations": [{"value": [0.002693603979423642], "step": 0}]}, "val_output_layer_1_binary_accuracy": {"direction": "min", "observations": [{"value": [0.976549506187439], "step": 0}]}, "val_output_layer_2_binary_accuracy": {"direction": "min", "observations": [{"value": [0.9572966992855072], "step": 0}]}}}, "score": 0.005572929745540023, "best_step": 0, "status": "COMPLETED"}