{"trial_id": "a3cc4c5deb8714299a3fbfc9f2f1c1a4", "hyperparameters": {"space": [{"class_name": "Int", "config": {"name": "nb_filters", "default": null, "conditions": [], "min_value": 32, "max_value": 512, "step": 32, "sampling": null}}, {"class_name": "Int", "config": {"name": "kernel_size", "default": null, "conditions": [], "min_value": 3, "max_value": 7, "step": 2, "sampling": null}}, {"class_name": "Float", "config": {"name": "learning_rate", "default": 0.001, "conditions": [], "min_value": 1e-05, "max_value": 0.01, "step": null, "sampling": "log"}}], "values": {"nb_filters": 288, "kernel_size": 7, "learning_rate": 0.0040429965958115955}}, "metrics": {"metrics": {"loss": {"direction": "min", "observations": [{"value": [0.003220168873667717], "step": 0}]}, "output_layer_1_loss": {"direction": "min", "observations": [{"value": [0.0014359147753566504], "step": 0}]}, "output_layer_2_loss": {"direction": "min", "observations": [{"value": [0.0017842526431195438], "step": 0}]}, "output_layer_1_binary_accuracy": {"direction": "min", "observations": [{"value": [0.9555825293064117], "step": 0}]}, "output_layer_2_binary_accuracy": {"direction": "min", "observations": [{"value": [0.9351341128349304], "step": 0}]}, "val_loss": {"direction": "min", "observations": [{"value": [0.00591618474572897], "step": 0}]}, "val_output_layer_1_loss": {"direction": "min", "observations": [{"value": [0.0024750340962782502], "step": 0}]}, "val_output_layer_2_loss": {"direction": "min", "observations": [{"value": [0.0034411505330353975], "step": 0}]}, "val_output_layer_1_binary_accuracy": {"direction": "min", "observations": [{"value": [0.9695367813110352], "step": 0}]}, "val_output_layer_2_binary_accuracy": {"direction": "min", "observations": [{"value": [0.9654337465763092], "step": 0}]}}}, "score": 0.00591618474572897, "best_step": 0, "status": "COMPLETED"}